metamart_graph/__init__.py
metamart_graph/analysis.py
metamart_graph/client_monkeypatch.py
metamart_graph/graph.py
metamart_graph/utils.py
metamart_graph/visualizations.py
metamart_graph-0.2.6.dist-info/METADATA
metamart_graph-0.2.6.dist-info/WHEEL
metamart_graph-0.2.6.dist-info/RECORD
