Metadata-Version: 2.1
Name: metamart-graph
Version: 0.2.6
Summary: 
Home-page: https://www.metamart.io/
License: Elastic-2.0
Author: Ian Eaves
Author-email: ian@metamart.io
Requires-Python: >=3.8,<4.0
Classifier: License :: Other/Proprietary License
Classifier: Programming Language :: Python :: 3
Classifier: Programming Language :: Python :: 3.8
Classifier: Programming Language :: Python :: 3.9
Classifier: Programming Language :: Python :: 3.10
Classifier: Programming Language :: Python :: 3.11
Classifier: Programming Language :: Python :: 3.12
Provides-Extra: vis
Requires-Dist: matplotlib (>=3.5.2,<4.0.0) ; extra == "vis"
Requires-Dist: metamart-client (>=0.3.0,<0.4.0)
Requires-Dist: metamart-schemas (>=0.2.0,<0.3.0)
Requires-Dist: multimethod (>=1.8,<2.0,!=1.11)
Requires-Dist: networkx (>=2.8.5,<3.0.0)
Requires-Dist: pydantic (>=1.9.1,<2.0.0)
Requires-Dist: pydot (>=1.4.2,<2.0.0) ; extra == "vis"
Project-URL: Documentation, https://docs.metamart.io/
Project-URL: Repository, https://github.com/meta-mart/metamart-core/tree/master/metamart-graph
